datatransformer/__init__.py
datatransformer/abstractobject.py
datatransformer/tensorflow/__init__.py
datatransformer/tensorflow/tensorflow_text.py
datatransformer-0.1.9.dist-info/LICENSE
datatransformer-0.1.9.dist-info/METADATA
datatransformer-0.1.9.dist-info/WHEEL
datatransformer-0.1.9.dist-info/top_level.txt
datatransformer-0.1.9.dist-info/RECORD
