Metadata-Version: 2.1
Name: datatransformer
Version: 0.1.9
Summary: A package for data transformation
Home-page: https://github.com/nextfortune/datatransformer.git
Author: Tim Su
Author-email: omg80827@gmail.com
License: UNKNOWN
Project-URL: Bug Tracker, https://github.com/nextfortune/datatransformer/issues
Platform: UNKNOWN
Classifier: Programming Language :: Python :: 3
Classifier: License :: OSI Approved :: MIT License
Classifier: Operating System :: OS Independent
Requires-Python: >=3.7
Requires-Dist: vaex (>=4.4.0)
Provides-Extra: tensorflow
Requires-Dist: tensorflow (>=2.7.0) ; extra == 'tensorflow'
Provides-Extra: tensorflow-gpu
Requires-Dist: tnesorflow-gpu (>=2.7.0) ; extra == 'tensorflow-gpu'
